MANIFEST.in
setup.py
lightcurve/__init__.py
lightcurve/analysis.py
lightcurve/cos.py
lightcurve/io.py
lightcurve/stis.py
lightcurve/utils.py
lightcurve/version.py
lightcurve.egg-info/PKG-INFO
lightcurve.egg-info/SOURCES.txt
lightcurve.egg-info/dependency_links.txt
lightcurve.egg-info/requires.txt
lightcurve.egg-info/top_level.txt
lightcurve/tests/__init__.py
lightcurve/tests/test_cos.py
lightcurve/tests/test_object.py
lightcurve/tests/test_stis_calib.py
lightcurve/tests/test_utils.py
scripts/lightcurve