Metadata-Version: 1.1
Name: lightcurve
Version: 0.6.1
Summary: Create lightcurves from HST/COS and HST/STIS data
Home-page: http://justincely.github.io/lightcurve/
Author: Justin Ely
Author-email: ely@stsci.edu
License: UNKNOWN
Keywords: astronomy
Platform: UNKNOWN
Classifier: Programming Language :: Python
Classifier: Programming Language :: Python :: 3
Classifier: Development Status :: 1 - Planning
Classifier: Intended Audience :: Science/Research
Classifier: Topic :: Scientific/Engineering :: Astronomy
Classifier: Topic :: Scientific/Engineering :: Physics
Classifier: Topic :: Software Development :: Libraries :: Python Modules
